flex_query/__init__.py
flex_query/generics.py
flex_query/manager.py
flex_query/models.py
flex_query/serializers.py
drf_flex_query-1.0.0.dist-info/LICENSE
drf_flex_query-1.0.0.dist-info/METADATA
drf_flex_query-1.0.0.dist-info/WHEEL
drf_flex_query-1.0.0.dist-info/top_level.txt
drf_flex_query-1.0.0.dist-info/RECORD
