Metadata-Version: 2.1
Name: drf-flex-query
Version: 1.0.0
Summary: Flexible related objects quering for Django REST Framework.
Home-page: https://github.com/Oper18/drf-flex-query
Author: Grigorii Novikov
Author-email: Grigorii Novikov <genovikov93@gmail.com>
License: MIT License
Project-URL: Homepage, https://github.com/Oper18/drf-flex-query
Project-URL: Issues, https://github.com/Oper18/drf-flex-query/issues
Keywords: django,rest,api,query
Classifier: Programming Language :: Python :: 3
Classifier: License :: OSI Approved :: MIT License
Classifier: Operating System :: OS Independent
Requires-Python: >=3.10
License-File: LICENSE
